{
  "api": "Figma API",
  "task": "Chad Ramsey / CareFlow Accessibility Triage",
  "purpose": "Provide current CareFlow Intake frames and design-token issue details.",
  "mock_calls": [
    {
      "method": "GET /v1/files/CF-INTAKE-REVIEW",
      "request": {
        "file_key": "CF-INTAKE-REVIEW"
      },
      "response": {
        "file_name": "CareFlow remediation review",
        "owner": "Chad Ramsey",
        "current_flow": "CareFlow Intake",
        "frames": [
          {
            "frame_id": "fig_frame_014",
            "frame_name": "Intake step 1",
            "issue_id": "INT-014",
            "current": true
          },
          {
            "frame_id": "fig_frame_018",
            "frame_name": "Intake error state",
            "issue_id": "INT-018",
            "current": true
          },
          {
            "frame_id": "fig_frame_021",
            "frame_name": "Intake mobile options",
            "issue_id": "INT-021",
            "current": true
          },
          {
            "frame_id": "fig_frame_024",
            "frame_name": "Intake insurance step",
            "issue_id": "INT-024",
            "current": true
          },
          {
            "frame_id": "fig_frame_018b",
            "frame_name": "Intake error state old duplicate",
            "issue_id": "INT-018B",
            "current": false
          }
        ]
      }
    },
    {
      "method": "GET /v1/files/CF-INTAKE-REVIEW/tokens",
      "request": {
        "file_key": "CF-INTAKE-REVIEW"
      },
      "response": {
        "token_findings": [
          {
            "issue_id": "INT-014",
            "finding": "low contrast primary action",
            "foreground": "#8FA0B5",
            "background": "#E7F1FD",
            "contrast_ratio": 2.9,
            "required_minimum": 4.5,
            "result": "fail",
            "priority": "P0"
          },
          {
            "issue_id": "INT-018",
            "finding": "focus order skips error summary",
            "current_order": "after field group",
            "expected_order": "before field group",
            "result": "fail",
            "priority": "P0"
          },
          {
            "issue_id": "INT-021",
            "finding": "mobile tap target below 44px",
            "current_size_px": 36,
            "required_size_px": 44,
            "result": "fail",
            "priority": "P1"
          },
          {
            "issue_id": "INT-024",
            "finding": "select field missing accessible name",
            "current_name": "Choose option",
            "expected_name": "Insurance plan type",
            "result": "fail",
            "priority": "P0"
          }
        ]
      }
    }
  ],
  "ground_truth_from_this_api": {
    "current_issue_ids": [
      "INT-014",
      "INT-018",
      "INT-021",
      "INT-024"
    ],
    "stale_duplicate": "INT-018B",
    "p0_count": 3,
    "p1_count": 1
  }
}